{
	"textures": {
		"0": "argentum:item/pelota",
		"particle": "argentum:item/pelota"
	},
	"elements": [
		{
			"from": [0, 0, 0],
			"to": [16, 16, 16],
			"faces": {
				"north": {"uv": [0, 0, 16, 16], "texture": "#0"},
				"east": {"uv": [0, 0, 16, 16], "texture": "#0"},
				"south": {"uv": [0, 0, 16, 16], "texture": "#0"},
				"west": {"uv": [0, 0, 16, 16], "texture": "#0"},
				"up": {"uv": [0, 0, 16, 16], "texture": "#0"},
				"down": {"uv": [0, 0, 16, 16], "texture": "#0"}
			}
		}
	],
	"display":  {
		"thirdperson_righthand":  {
			"rotation":  [
				73,
				0,
				0
			],
			"translation":  [
				0,
				2,
				-2
			],
			"scale":  [
				0.3,
				0.3,
				0.3
			]
		},
		"firstperson_righthand":  {
			"rotation":  [
				0,
				0,
				0
			],
			"translation":  [
				1.13,
				3.2,
				1.13
			],
			"scale":  [
				0.3,
				0.3,
				0.3
			]
		},
		"firstperson_lefthand":  {
			"rotation":  [
				0,
				0,
				0
			],
			"translation":  [
				1.13,
				3.2,
				1.13
			],
			"scale":  [
				0.3,
				0.3,
				0.3
			]
		},
		"thirdperson_lefthand":  {
			"rotation":  [
				73,
				0,
				0
			],
			"translation":  [
				0,
				2,
				-2
			],
			"scale":  [
				0.3,
				0.3,
				0.3
			]
		},
		"gui":  {
			"rotation":  [
				30,
				225,
				0
			],
			"translation":  [
				0,
				-0.3,
				0
			],
			"scale":  [
				0.45,
				0.45,
				0.45
			]
		},
		"ground":  {
			"rotation":  [
				0,
				0,
				0
			],
			"translation":  [
				0,
				3,
				0
			],
			"scale":  [
				0.4,
				0.4,
				0.4
			]
		},
		"fixed":  {
			"rotation":  [
				0,
				0,
				0
			],
			"translation":  [
				0,
				0,
				0
			],
			"scale":  [
				0.5,
				0.5,
				0.5
			]
		}
	}
}
